LaplaPy/__init__.py
LaplaPy/cli.py
LaplaPy/core.py
laplapy-0.2.6.dist-info/licenses/LICENSE
laplapy-0.2.6.dist-info/METADATA
laplapy-0.2.6.dist-info/WHEEL
laplapy-0.2.6.dist-info/entry_points.txt
laplapy-0.2.6.dist-info/top_level.txt
laplapy-0.2.6.dist-info/RECORD
