Metadata-Version: 2.4
Name: LaplaPy
Version: 0.2.6
Summary: Symbolic Laplace transforms & ODE solving with step-by-step output
Author-email: GALIH RIDHO UTOMO <g4lihru@students.unnes.ac.id>
License: MIT
Project-URL: Homepage, https://github.com/galihru/LaplaPy
Project-URL: Repository, https://github.com/galihru/LaplaPy
Classifier: Programming Language :: Python :: 3
Classifier: License :: OSI Approved :: MIT License
Classifier: Topic :: Scientific/Engineering :: Mathematics
License-File: LICENSE
Requires-Dist: sympy>=1.10
Requires-Dist: numpy
Dynamic: license-file
